hifi_trimmer/BamFilterer.py
hifi_trimmer/BlastProcessor.py
hifi_trimmer/SummariseBlastResults.py
hifi_trimmer/__init__.py
hifi_trimmer/hifi_trimmer.py
hifi_trimmer-2.1.0.dist-info/METADATA
hifi_trimmer-2.1.0.dist-info/WHEEL
hifi_trimmer-2.1.0.dist-info/entry_points.txt
hifi_trimmer-2.1.0.dist-info/licenses/LICENSE
hifi_trimmer-2.1.0.dist-info/RECORD
