Metadata-Version: 2.4
Name: hifi_trimmer
Version: 2.1.0
Summary: hifi_trimmer is a tool for filtering and trimming extraneous adapter hits from a HiFi read set using a BLAST search.
Project-URL: Homepage, https://github.com/sanger-tol/hifi-trimmer/
Project-URL: Issues, https://github.com/sanger-tol/hifi-trimmer/issues
Author-email: Jim Downie <jd42@sanger.ac.uk>
License-Expression: MIT
License-File: LICENSE
Classifier: Operating System :: OS Independent
Classifier: Programming Language :: Python :: 3
Requires-Python: <3.13,>=3.10
Requires-Dist: bgzip>=0.5.0
Requires-Dist: click>=8.1.8
Requires-Dist: polars<=1.22.0
Requires-Dist: pysam>=0.23.0
Requires-Dist: pyyaml>=6.0.2
